utic_public_types/__init__.py
utic_public_types/plugins/__init__.py
utic_public_types/plugins/defaults.py
utic_public_types/plugins/errors.py
utic_public_types/plugins/file_data.py
utic_public_types/plugins/json_schema.py
utic_public_types/plugins/models.py
utic_public_types/plugins/taxonomy.py
utic_public_types/plugins/usage.py
utic_public_types/plugins/api/README.md
utic_public_types/plugins/api/generate_openapi.py
utic_public_types/plugins/api/openapi-draft.yaml
utic_public_types/plugins/api/requirements.txt
utic_public_types-0.3.6.dist-info/METADATA
utic_public_types-0.3.6.dist-info/WHEEL
utic_public_types-0.3.6.dist-info/RECORD
