Metadata-Version: 2.4
Name: utic-public-types
Version: 0.3.6
Summary: Public/Open types shared among different projects in the Unstructured.io ecosystem.
Requires-Python: >=3.10
Requires-Dist: openapi-pydantic
Requires-Dist: pydantic
Requires-Dist: pydantic-settings
Requires-Dist: pyyaml
